awsec/__init__.py
awsec-0.0.1.dist-info/LICENSE
awsec-0.0.1.dist-info/WHEEL
awsec-0.0.1.dist-info/METADATA
awsec-0.0.1.dist-info/RECORD
